ilovepythonn/__init__.py
ilovepythonn/desktop.ini
ilovepythonn-1.0.dist-info/METADATA
ilovepythonn-1.0.dist-info/WHEEL
ilovepythonn-1.0.dist-info/top_level.txt
ilovepythonn-1.0.dist-info/RECORD
