Metadata-Version: 2.4
Name: ilovepythonn
Version: 1.0
Summary: The true love to python :D
Home-page: https://github.com/SuperZombi/Pypi-uploader
Author: CtrlZett
Author-email: Ivansharkov2012@gmail.com
Classifier: Programming Language :: Python :: 3
Classifier: License :: OSI Approved :: MIT License
Classifier: Operating System :: OS Independent
Requires-Python: >=3.13
Dynamic: author
Dynamic: author-email
Dynamic: classifier
Dynamic: description
Dynamic: description-content-type
Dynamic: home-page
Dynamic: requires-python
Dynamic: summary
